bids_phenotype/cli.py
bids_phenotype/datasets/ABCD_4.py
bids_phenotype/datasets/ABIDE_I.py
bids_phenotype/datasets/ABIDE_II.py
bids_phenotype/datasets/HBN.py
bids_phenotype/datasets/HCP_1200.py
bids_phenotype/datasets/NKI.py
bids_phenotype/datasets/PNC.py
bids_phenotype/datasets/UKB.py
bids_phenotype/datasets/fixed_dicts/ABCD_4_nda_data_structure_definitions/abcd_abcls01.csv
bids_phenotype/datasets/fixed_dicts/ABCD_4_nda_data_structure_definitions/abcd_adbc01.csv
bids_phenotype/datasets/fixed_dicts/ABCD_4_nda_data_structure_definitions/abcd_ant01.csv
bids_phenotype/datasets/fixed_dicts/ABCD_4_nda_data_structure_definitions/abcd_asrs01.csv
bids_phenotype/datasets/fixed_dicts/ABCD_4_nda_data_structure_definitions/abcd_auto_postqc01.csv
bids_phenotype/datasets/fixed_dicts/ABCD_4_nda_data_structure_definitions/abcd_betnet02.csv
bids_phenotype/datasets/fixed_dicts/ABCD_4_nda_data_structure_definitions/abcd_bisbas01.csv
bids_phenotype/datasets/fixed_dicts/ABCD_4_nda_data_structure_definitions/abcd_bkfs01.csv
bids_phenotype/datasets/fixed_dicts/ABCD_4_nda_data_structure_definitions/abcd_bp01.csv
bids_phenotype/datasets/fixed_dicts/ABCD_4_nda_data_structure_definitions/abcd_bpm01.csv
bids_phenotype/datasets/fixed_dicts/ABCD_4_nda_data_structure_definitions/abcd_bpmt01.csv
bids_phenotype/datasets/fixed_dicts/ABCD_4_nda_data_structure_definitions/abcd_cb01.csv
bids_phenotype/datasets/fixed_dicts/ABCD_4_nda_data_structure_definitions/abcd_cbcl01.csv
bids_phenotype/datasets/fixed_dicts/ABCD_4_nda_data_structure_definitions/abcd_cbcls01.csv
bids_phenotype/datasets/fixed_dicts/ABCD_4_nda_data_structure_definitions/abcd_cna01.csv
bids_phenotype/datasets/fixed_dicts/ABCD_4_nda_data_structure_definitions/abcd_crpf01.csv
bids_phenotype/datasets/fixed_dicts/ABCD_4_nda_data_structure_definitions/abcd_ddtidp101.csv
bids_phenotype/datasets/fixed_dicts/ABCD_4_nda_data_structure_definitions/abcd_ddtidp201.csv
bids_phenotype-2.0.0.dist-info/LICENSE
bids_phenotype-2.0.0.dist-info/METADATA
bids_phenotype-2.0.0.dist-info/WHEEL
bids_phenotype-2.0.0.dist-info/entry_points.txt
bids_phenotype-2.0.0.dist-info/RECORD
